nonebot_plugin_chatgpt_turbo/__init__.py
nonebot_plugin_chatgpt_turbo/config.py
nonebot_plugin_chatgpt_turbo-1.2.1.dist-info/METADATA
nonebot_plugin_chatgpt_turbo-1.2.1.dist-info/WHEEL
nonebot_plugin_chatgpt_turbo-1.2.1.dist-info/RECORD
