Metadata-Version: 2.1
Name: nonebot-plugin-chatgpt-turbo
Version: 1.2.1
Summary: A nonebot plugin for oneapi and openai
License: MIT
Author: Alpaca
Author-email: alpaca@bupt.edu.cn
Requires-Python: >=3.8,<4.0
Classifier: License :: OSI Approved :: MIT License
Classifier: Programming Language :: Python :: 3
Classifier: Programming Language :: Python :: 3.8
Classifier: Programming Language :: Python :: 3.9
Classifier: Programming Language :: Python :: 3.10
Classifier: Programming Language :: Python :: 3.11
Classifier: Programming Language :: Python :: 3.12
Classifier: Programming Language :: Python :: 3.13
Requires-Dist: nonebot-adapter-onebot (>=2.2.1,<3.0.0)
Requires-Dist: nonebot-plugin-send-anything-anywhere (>=0.7.1,<0.8.0)
Requires-Dist: nonebot2 (>=2.2.0,<3.0.0)
Requires-Dist: openai (>=1.55.3,<2.0.0)
